Metadata-Version: 1.1
Name: herokupackage
Version: 0.1.0
Summary: heroku package
Home-page: UNKNOWN
Author: Yang
Author-email: yoyoo6021@hotmail.com
License: MIT
Platform: UNKNOWN
Classifier: Development Status :: 5 - Production/Stable
Classifier: Intended Audience :: Education
Classifier: License :: OSI Approved :: MIT License
Classifier: Programming Language :: Python :: 3
